sema4ai/actions/__init__.py
sema4ai/actions/__main__.py
sema4ai/actions/_action.py
sema4ai/actions/_action_context.py
sema4ai/actions/_args_dispatcher.py
sema4ai/actions/_callback.py
sema4ai/actions/_collect_actions.py
sema4ai/actions/_commands.py
sema4ai/actions/_config.py
sema4ai/actions/_constants.py
sema4ai/actions/_customization/__init__.py
sema4ai/actions/_customization/_extension_points.py
sema4ai/actions/_customization/_plugin_manager.py
sema4ai/actions/_exceptions.py
sema4ai/actions/_fixtures.py
sema4ai/actions/_hooks.py
sema4ai/actions/_interrupts.py
sema4ai/actions/_lifecycle.py
sema4ai/actions/_lint_action.py
sema4ai/actions/_log_auto_setup.py
sema4ai/actions/_log_output_setup.py
sema4ai/actions/_managed_parameters.py
sema4ai/actions/_protocols.py
sema4ai/actions/_raw_types_handler.py
sema4ai/actions/_remove_refs.py
sema4ai/actions/_request.py
sema4ai/actions/_request_impl.py
sema4ai/actions/_response.py
sema4ai/actions/_secret/__init__.py
sema4ai/actions/_secret/_oauth2_secret.py
sema4ai/actions/_secret/_secret.py
sema4ai/actions/_table.py
sema4ai/actions/_uris.py
sema4ai/actions/_variables_scope.py
sema4ai/actions/agent/__init__.py
sema4ai/actions/agent/_client.py
sema4ai/actions/agent/_models.py
sema4ai/actions/agent/_platforms.py
sema4ai/actions/agent/_response.py
sema4ai/actions/api.py
sema4ai/actions/chat/__init__.py
sema4ai/actions/chat/_client.py
sema4ai/actions/cli.py
sema4ai/actions/py.typed
sema4ai_actions-1.6.5.dist-info/METADATA
sema4ai_actions-1.6.5.dist-info/WHEEL
sema4ai_actions-1.6.5.dist-info/RECORD
