Metadata-Version: 2.4
Name: sema4ai-actions
Version: 1.6.5
Summary: Sema4AI Actions
License: Apache-2.0
Author: Sema4.ai Engineering
Author-email: engineering@sema4.ai
Requires-Python: >=3.10,<4.0
Classifier: License :: OSI Approved :: Apache Software License
Classifier: Programming Language :: Python :: 3
Classifier: Programming Language :: Python :: 3.10
Classifier: Programming Language :: Python :: 3.11
Classifier: Programming Language :: Python :: 3.12
Classifier: Programming Language :: Python :: 3.13
Classifier: Programming Language :: Python :: 3.14
Requires-Dist: cryptography (>=44.0.1)
Requires-Dist: docstring_parser_fork (>=0.0.5,<0.0.6)
Requires-Dist: psutil (>=5.0,<8.0)
Requires-Dist: pydantic (>=2.11.7,<3.0.0)
Requires-Dist: pyyaml (>=6.0,<7.0)
Requires-Dist: robocorp-log (>=2.4,<4)
Requires-Dist: robocorp-truststore (>=0.8.0)
Requires-Dist: sema4ai-http-helper (>=2.0.1,<3.0.0)
Project-URL: Repository, https://github.com/Sema4AI/actions/
